function/function.py
setreq-0.0.7.dist-info/LICENSE
setreq-0.0.7.dist-info/METADATA
setreq-0.0.7.dist-info/WHEEL
setreq-0.0.7.dist-info/top_level.txt
setreq-0.0.7.dist-info/RECORD
